{"plots":[{"plot_crop_name":"Carrots","plot_crop_stage":3},{"plot_crop_name":"Carrots","plot_crop_stage":3},{"plot_crop_name":"Carrots","plot_crop_stage":3},{"plot_crop_name":"Carrots","plot_crop_stage":3},{"plot_crop_name":"Carrots","plot_crop_stage":3},{"plot_crop_name":"Carrots","plot_crop_stage":3},{"plot_crop_name":"Carrots","plot_crop_stage":3},{"plot_crop_name":"Carrots","plot_crop_stage":3},{"plot_crop_name":"Carrots","plot_crop_stage":3},{"plot_crop_name":"Carrots","plot_crop_stage":3},{"plot_crop_name":"Carrots","plot_crop_stage":3},{"plot_crop_name":"Carrots","plot_crop_stage":3},{"plot_crop_name":"Carrots","plot_crop_stage":3},{"plot_crop_name":"Carrots","plot_crop_stage":3},{"plot_crop_name":"Carrots","plot_crop_stage":3},{"plot_crop_name":"Carrots","plot_crop_stage":3},{"plot_crop_name":"Potatoes","plot_crop_stage":3},{"plot_crop_name":"Potatoes","plot_crop_stage":3},{"plot_crop_name":"Potatoes","plot_crop_stage":3},{"plot_crop_name":"Potatoes","plot_crop_stage":3},{"plot_crop_name":"Potatoes","plot_crop_stage":3},{"plot_crop_name":"Potatoes","plot_crop_stage":3},{"plot_crop_name":"Potatoes","plot_crop_stage":3},{"plot_crop_name":"Potatoes","plot_crop_stage":3},{"plot_crop_name":"Potatoes","plot_crop_stage":3}],"resources":{"Carrots":290,"Coins":415,"Potatoes":0}}
